downloader/__init__.py
downloader/datasets.py
downloader/models.py
downloader/types.py
downloader/utils.py
downloader/tests/__init__.py
downloader/tests/test_dataset_download.py
downloader/tests/test_model_download.py
tests/__init__.py
tests/conftest.py
tests/pytorch_tests/__init__.py
tests/pytorch_tests/test_image_anomaly_detection.py
tests/pytorch_tests/test_image_classification.py
tests/pytorch_tests/test_text_classification.py
tests/pytorch_tests/test_text_generation.py
tests/pytorch_tests/unit/__init__.py
tests/pytorch_tests/unit/test_datasets.py
tests/pytorch_tests/unit/test_inc.py
tests/pytorch_tests/unit/test_models.py
tests/tensorflow_tests/__init__.py
tests/tensorflow_tests/test_image_classification.py
tests/tensorflow_tests/test_text_classification.py
tests/tensorflow_tests/unit/__init__.py
tests/tensorflow_tests/unit/test_datasets.py
tests/tensorflow_tests/unit/test_inc.py
tests/tensorflow_tests/unit/test_models.py
tests/test_utils/__init__.py
tests/test_utils/platform_config.py
tests/tools/__init__.py
tests/tools/cli/__init__.py
tests/tools/cli/test_benchmark_cli.py
tests/tools/cli/test_eval_cli.py
tests/tools/cli/test_generate_cli.py
tests/tools/cli/test_optimize_cli.py
tests/tools/cli/test_quantize_cli.py
tests/tools/cli/test_train_cli.py
tests/utils/__init__.py
tests/utils/test_file_utils.py
tests/utils/test_inc_utils.py
tests/utils/test_platform_util.py
tlt/__init__.py
tlt/datasets/__init__.py
tlt/datasets/dataset.py
tlt/datasets/dataset_factory.py
tlt/datasets/hf_dataset.py
tlt/datasets/pytorch_dataset.py
tlt/datasets/tf_dataset.py
tlt/datasets/configs/hf_text_classification_datasets.json
tlt/datasets/configs/tf_text_classification_datasets.json
tlt/datasets/image_anomaly_detection/__init__.py
tlt/datasets/image_anomaly_detection/pytorch_custom_image_anomaly_detection_dataset.py
tlt/datasets/image_classification/__init__.py
tlt/datasets/image_classification/image_classification_dataset.py
intel_transfer_learning_tool-0.6.0.dist-info/LICENSE
intel_transfer_learning_tool-0.6.0.dist-info/METADATA
intel_transfer_learning_tool-0.6.0.dist-info/WHEEL
intel_transfer_learning_tool-0.6.0.dist-info/entry_points.txt
intel_transfer_learning_tool-0.6.0.dist-info/top_level.txt
intel_transfer_learning_tool-0.6.0.dist-info/RECORD
