Metadata-Version: 2.1
Name: intel-transfer-learning-tool
Version: 0.6.0
Summary: Intel® Transfer Learning Tool
Home-page: https://github.com/IntelAI/transfer-learning
Author: IntelAI
Author-email: IntelAI@intel.com
License: Apache 2.0
Requires-Python: >=3.8
License-File: LICENSE
Requires-Dist: click
Requires-Dist: charset-normalizer ==3.3.0
Requires-Dist: datasets ==2.14.5
Requires-Dist: intel-extension-for-pytorch ==1.13.100
Requires-Dist: neural-compressor ==2.1.1
Requires-Dist: peft ==0.3.0
Requires-Dist: protobuf ==4.24.4
Requires-Dist: python-dateutil ==2.8.2
Requires-Dist: torch ==1.13.1
Requires-Dist: torchvision ==0.14.1
Requires-Dist: transformers[torch] ==4.34.0
Requires-Dist: intel-tensorflow ==2.12.0
Requires-Dist: numpy ==1.23.5
Requires-Dist: tensorflow-hub ==0.15.0
Requires-Dist: transformers[tensorflow] ==4.34.0
Requires-Dist: tensorflow-datasets ==4.9.2 ; python_version == "3.8"
Requires-Dist: tensorflow-datasets ==4.9.3 ; python_version > "3.8"
Provides-Extra: pytorch
Requires-Dist: charset-normalizer ==3.3.0 ; extra == 'pytorch'
Requires-Dist: datasets ==2.14.5 ; extra == 'pytorch'
Requires-Dist: intel-extension-for-pytorch ==1.13.100 ; extra == 'pytorch'
Requires-Dist: neural-compressor ==2.1.1 ; extra == 'pytorch'
Requires-Dist: peft ==0.3.0 ; extra == 'pytorch'
Requires-Dist: protobuf ==4.24.4 ; extra == 'pytorch'
Requires-Dist: python-dateutil ==2.8.2 ; extra == 'pytorch'
Requires-Dist: torch ==1.13.1 ; extra == 'pytorch'
Requires-Dist: torchvision ==0.14.1 ; extra == 'pytorch'
Requires-Dist: transformers[torch] ==4.34.0 ; extra == 'pytorch'
Provides-Extra: tensorflow
Requires-Dist: intel-tensorflow ==2.12.0 ; extra == 'tensorflow'
Requires-Dist: neural-compressor ==2.1.1 ; extra == 'tensorflow'
Requires-Dist: numpy ==1.23.5 ; extra == 'tensorflow'
Requires-Dist: tensorflow-hub ==0.15.0 ; extra == 'tensorflow'
Requires-Dist: transformers[tensorflow] ==4.34.0 ; extra == 'tensorflow'
Requires-Dist: tensorflow-datasets ==4.9.2 ; (python_version == "3.8") and extra == 'tensorflow'
Requires-Dist: tensorflow-datasets ==4.9.3 ; (python_version > "3.8") and extra == 'tensorflow'
